{
  "todos": [
    {
      "id": "1",
      "title": "Learn ReactJs and NodeJS",
      "status": "completed",
      "priority": "medium"
    },
    {
      "id": "2",
      "title": "Coding Todo List",
      "status": "completed",
      "priority": "high"
    },
    {
      "id": "3",
      "title": "Review HTML5, CSS3 and Senmatic HTML",
      "status": "incomplete",
      "priority": "low"
    },
    {
      "id": "4",
      "title": "Learn English for Coding",
      "status": "completed",
      "priority": "medium"
    },
    {
      "id": "e7f5",
      "title": "add",
      "priority": "medium",
      "status": "completed"
    },
    {
      "id": "cd28",
      "title": "add",
      "priority": "medium",
      "status": "completed"
    },
    {
      "id": "8b9c",
      "title": "add",
      "priority": "medium",
      "status": "incomplete"
    },
    {
      "id": "7d29",
      "title": "add",
      "priority": "medium",
      "status": "completed"
    },
    {
      "id": "b832",
      "title": "add",
      "priority": "medium",
      "status": "incomplete"
    },
    {
      "id": "fc26",
      "title": "add",
      "priority": "medium",
      "status": "incomplete"
    },
    {
      "id": "a9cf",
      "title": "haha",
      "priority": "medium",
      "status": "incomplete"
    },
    {
      "id": "1465",
      "title": "haha",
      "priority": "medium",
      "status": "incomplete"
    },
    {
      "id": "5df8",
      "title": "thêm task",
      "priority": "medium",
      "status": "incomplete"
    },
    {
      "id": "8c62",
      "title": "Learn",
      "priority": "medium",
      "status": "incomplete"
    },
    {
      "id": "18a6",
      "title": "<add",
      "priority": "medium",
      "status": "incomplete"
    },
    {
      "id": "e40a",
      "title": "dsadsa<",
      "priority": "medium",
      "status": "incomplete"
    },
    {
      "id": "b413",
      "title": "jkajdksa",
      "priority": "medium",
      "status": "incomplete"
    },
    {
      "id": "679e",
      "title": "dsa",
      "priority": "medium",
      "status": "incomplete"
    },
    {
      "id": "45e2",
      "title": "dsdsadsaaxac",
      "priority": "medium",
      "status": "incomplete"
    },
    {
      "id": "8b0d",
      "title": "haha haha",
      "priority": "medium",
      "status": "incomplete"
    },
    {
      "id": "6db2",
      "title": "learing h",
      "priority": "medium",
      "status": "incomplete"
    }
  ]
}